gregex/__init__.py
gregex/char.py
gregex/group.py
gregex/pattern.py
gregex/repeat.py
gregex/set.py
gregex/unicode.py
gregex/version.py
gregex-0.0.1.dist-info/METADATA
gregex-0.0.1.dist-info/WHEEL
gregex-0.0.1.dist-info/licenses/LICENSE
gregex-0.0.1.dist-info/RECORD
