Metadata-Version: 2.4
Name: gregex
Version: 0.0.1
Summary: gregex
Project-URL: Homepage, https://github.com/jiauzhang/gregex
Author-email: Jiau Zhang <jiauzhang@163.com>
License:                     GNU GENERAL PUBLIC LICENSE
License-File: LICENSE
Requires-Python: >=3.8
Provides-Extra: dev
Requires-Dist: pytest>=8.3.4; extra == 'dev'
